{
  "name": "Lemon Cake",
  "ingredients": [
    {
      "name": "Self Raising Flour",
      "quantity": 8,
      "unit": "oz"
    },
    {
      "name": "Butter",
      "quantity": 8,
      "unit": "oz"
    },
    {
      "name": "Caster Sugar",
      "quantity": 6,
      "unit": "oz"
    },
    {
      "name": "Eggs",
      "quantity": 3,
      "unit": ""
    },
    {
      "name": "Lemon",
      "quantity": 1,
      "unit": "",
      "notes": "juice and rind"
    },
    {
      "name": "Lemon",
      "quantity": 1,
      "unit": "",
      "notes": "juice"
    },
    {
      "name": "Caster Sugar",
      "quantity": 6,
      "unit": "oz"
    }
  ],
  "steps": [
    {
      "name": "Cream",
      "description": "Cream until light and fluffy",
      "ingredients": [1, 2]
    },
    {
      "name": "Eggs",
      "description": "Add gradually",
      "ingredients": [3]
    },
    {
      "name": "Flour",
      "description": "Add gradually",
      "ingredients": [0, 4]
    },
    {
      "name": "Bake",
      "description": "Bake for 30 mins at 160 in oblong tray",
      "ingredients": []
    },
    {
      "name": "Drizzle",
      "description": "Mix then pour over pricked cake",
      "ingredients": [5, 6]
    }
  ],
  "yield": 1,
  "yieldUnit": ""
}