{
  "name": "Smoked Lamb Leg",
  "yield": 1,
  "yieldUnit": "Leg",
  "ingredients": [
    {
      "name": "Lamb leg",
      "quantity": 1
    },
    {
      "name": "Salt",
      "quantity": 2,
      "unit": "tbsp"
    },
    {
      "name": "Butter",
      "quantity": 50,
      "unit": "g"
    },
    {
      "name": "Rosemary",
      "quantity": 20,
      "unit": "g",
      "notes": "fresh"
    },
    {
      "name": "Garlic",
      "quantity": 6,
      "unit": "cloves"
    },
    {
      "name": "Salt",
      "quantity": 1,
      "unit": "tbsp"
    },
    {
      "name": "Pepper",
      "quantity": 2,
      "unit": "tbsp"
    }
  ],
  "steps": [
    {
      "id": 0,
      "name": "Dry brine",
      "description": "Rub the salt all over the lamb leg and leave in the fridge for 12-18 hours",
      "ingredients": [
        0,
        1
      ]
    },
    {
      "id": 1,
      "name": "Glaze",
      "description": "Melt the butter and mix with finely chopped rosemary, crushed garlic, salt and pepper",
      "ingredients": [
        2,
        3,
        4,
        5,
        6
      ]
    },
    {
      "id": 2,
      "name": "Smoke",
      "description": "Brush the glaze over the lamb leg and smoke for 4 hours at 120°",
      "ingredients": []
    }
  ]
}